MANIFEST.in
README.txt
setup.cfg
setup.py
charset/__init__.py
charset/cmd.py
charset.egg-info/PKG-INFO
charset.egg-info/SOURCES.txt
charset.egg-info/dependency_links.txt
charset.egg-info/entry_points.txt
charset.egg-info/not-zip-safe
charset.egg-info/requires.txt
charset.egg-info/top_level.txt
src/charset.detector.cpp
src/charset.detector.pyx
src/mozilladetector/Big5Freq.tab
src/mozilladetector/CharDistribution.cpp
src/mozilladetector/CharDistribution.h
src/mozilladetector/EUCKRFreq.tab
src/mozilladetector/EUCTWFreq.tab
src/mozilladetector/GB2312Freq.tab
src/mozilladetector/JISFreq.tab
src/mozilladetector/JpCntx.cpp
src/mozilladetector/JpCntx.h
src/mozilladetector/LangBulgarianModel.cpp
src/mozilladetector/LangCyrillicModel.cpp
src/mozilladetector/LangGreekModel.cpp
src/mozilladetector/LangHebrewModel.cpp
src/mozilladetector/LangHungarianModel.cpp
src/mozilladetector/LangThaiModel.cpp
src/mozilladetector/Makefile.in
src/mozilladetector/detector.cpp
src/mozilladetector/detector.h
src/mozilladetector/nsBig5Prober.cpp
src/mozilladetector/nsBig5Prober.h
src/mozilladetector/nsCharSetProber.cpp
src/mozilladetector/nsCharSetProber.h
src/mozilladetector/nsCodingStateMachine.h
src/mozilladetector/nsEUCJPProber.cpp
src/mozilladetector/nsEUCJPProber.h
src/mozilladetector/nsEUCKRProber.cpp
src/mozilladetector/nsEUCKRProber.h
src/mozilladetector/nsEUCTWProber.cpp
src/mozilladetector/nsEUCTWProber.h
src/mozilladetector/nsEscCharsetProber.cpp
src/mozilladetector/nsEscCharsetProber.h
src/mozilladetector/nsEscSM.cpp
src/mozilladetector/nsGB2312Prober.cpp
src/mozilladetector/nsGB2312Prober.h
src/mozilladetector/nsHebrewProber.cpp
src/mozilladetector/nsHebrewProber.h
src/mozilladetector/nsLatin1Prober.cpp
src/mozilladetector/nsLatin1Prober.h
src/mozilladetector/nsMBCSGroupProber.cpp
src/mozilladetector/nsMBCSGroupProber.h
src/mozilladetector/nsMBCSSM.cpp
src/mozilladetector/nsPkgInt.h
src/mozilladetector/nsSBCSGroupProber.cpp
src/mozilladetector/nsSBCSGroupProber.h
src/mozilladetector/nsSBCharSetProber.cpp
src/mozilladetector/nsSBCharSetProber.h
src/mozilladetector/nsSJISProber.cpp
src/mozilladetector/nsSJISProber.h
src/mozilladetector/nsUTF8Prober.cpp
src/mozilladetector/nsUTF8Prober.h
