Metadata-Version: 1.0
Name: charset
Version: 1.0.1
Summary: Clases for charset detection. Uses chardet and mozilla universal charset detection.
Home-page: UNKNOWN
Author: Karel Antonio Verdecia Ortiz
Author-email: kverdecia@uci.cu, kverdecia@gmail.com
License: MPL 2.0
Platform: UNKNOWN
